timewatcher/__init__.py
timewatcher/app.py
timewatcher/configs.py
timewatcher/consts.py
timewatcher/data.py
timewatcher/timewatcher.py
timewatcher-2.2.1.dist-info/LICENSE
timewatcher-2.2.1.dist-info/METADATA
timewatcher-2.2.1.dist-info/WHEEL
timewatcher-2.2.1.dist-info/entry_points.txt
timewatcher-2.2.1.dist-info/RECORD
