Metadata-Version: 2.1
Name: timewatcher
Version: 2.2.1
Summary: Automatically update hours card on TimeWatch
License: MIT
Author: Gal Birka
Author-email: birkagal@gmail.com
Requires-Python: >=3.11,<4.0
Classifier: License :: OSI Approved :: MIT License
Classifier: Programming Language :: Python :: 3
Classifier: Programming Language :: Python :: 3.11
Classifier: Programming Language :: Python :: 3.12
Requires-Dist: bs4 (>=0.0.2,<0.0.3)
Requires-Dist: pyfiglet (>=1.0.2,<2.0.0)
Requires-Dist: requests (>=2.31.0,<3.0.0)
Requires-Dist: termcolor (>=2.4.0,<3.0.0)
Project-URL: Source, https://github.com/birkagal/timewatcher
